README.md
setup.py
timi_robot/__init__.py
timi_robot/hub.py
timi_robot/logger.py
timi_robot/robot.py
timi_robot.egg-info/PKG-INFO
timi_robot.egg-info/SOURCES.txt
timi_robot.egg-info/dependency_links.txt
timi_robot.egg-info/requires.txt
timi_robot.egg-info/top_level.txt