Metadata-Version: 2.1
Name: timi-robot
Version: 1.3.0
Summary: 基于机器微信机器人实现的线上日志错误回调。
Home-page: https://github.com/lxl0928/wechat_work_logger_robot
Author: Timi long
Author-email: lixiaolong@smuer.cn
License: UNKNOWN
Platform: UNKNOWN
Classifier: Development Status :: 5 - Production/Stable
Classifier: Intended Audience :: Developers
Classifier: License :: OSI Approved :: BSD License
Classifier: Operating System :: OS Independent
Classifier: Programming Language :: Python
Classifier: Programming Language :: Python :: 3.6
Classifier: Programming Language :: Python :: 3.7
Provides-Extra: requests
